pdm_audit_plugin/__init__.py
pdm_audit_plugin/commands.py
pdm_audit_plugin-0.1.2.dist-info/METADATA
pdm_audit_plugin-0.1.2.dist-info/WHEEL
pdm_audit_plugin-0.1.2.dist-info/entry_points.txt
pdm_audit_plugin-0.1.2.dist-info/top_level.txt
pdm_audit_plugin-0.1.2.dist-info/RECORD
