Metadata-Version: 2.1
Name: pdm-audit-plugin
Version: 0.1.2
Summary: Default template for PDM package
Author-email: Manjusaka <me@manjusaka.me>
License: MIT
Project-URL: Repository, https://github.com/Zheaoli/pdm-audit
Project-URL: Homepage, https://github.com/Zheaoli/pdm-audit
Requires-Python: >=3.9
Requires-Dist: pip-audit>=2.7.3
Provides-Extra: pytest
Requires-Dist: pytest; extra == "pytest"
Requires-Dist: pytest-mock; extra == "pytest"
